fernet_files/__init__.py
fernet_files/custom_fernet.py
fernet_files-0.1.1.dist-info/LICENSE
fernet_files-0.1.1.dist-info/METADATA
fernet_files-0.1.1.dist-info/WHEEL
fernet_files-0.1.1.dist-info/top_level.txt
fernet_files-0.1.1.dist-info/RECORD
