Metadata-Version: 2.1
Name: fernet_files
Version: 0.1.1
Summary: Encryption/decryption of files with cryptography.fernet, but with file-like methods
Author-email: Christopher Ashford <christopherash0605@gmail.com>
Project-URL: repository, https://github.com/Kris-0605/fernet-files
Keywords: fernet,fernetfile,fernet_file,fernetfiles
Classifier: Development Status :: 3 - Alpha
Classifier: Intended Audience :: Developers
Classifier: License :: OSI Approved :: MIT License
Classifier: Natural Language :: English
Classifier: Programming Language :: Python
Classifier: Programming Language :: Python :: 3.10
Classifier: Topic :: File Formats
Requires-Python: >=3.10
License-File: LICENSE
Requires-Dist: cryptography <=42.0.2,>=36.0.2
